arkid_client/__init__.py
arkid_client/base.py
arkid_client/client.py
arkid_client/config.py
arkid_client/exceptions.py
arkid_client/oneid.cfg
arkid_client/response.py
arkid_client/version.py
arkid_client/auth/__init__.py
arkid_client/auth/client/__init__.py
arkid_client/auth/client/base.py
arkid_client/auth/client/confidential_client.py
arkid_client/authorizers/__init__.py
arkid_client/authorizers/access_token.py
arkid_client/authorizers/base.py
arkid_client/authorizers/basic.py
arkid_client/authorizers/null.py
arkid_client/configuration/__init__.py
arkid_client/configuration/client.py
arkid_client/dept/__init__.py
arkid_client/dept/client.py
arkid_client/node/__init__.py
arkid_client/node/client.py
arkid_client/org/__init__.py
arkid_client/org/client.py
arkid_client/user/__init__.py
arkid_client/user/client.py
arkid_client/utils/__init__.py
arkid_client/utils/string_hashing.py
tests/__init__.py
tests/common.py
tests/client/__init__.py
tests/client/test_auth.py
tests/client/test_node.py
tests/client/test_org.py
tests/client/test_user.py
arkid_client-0.1.0.dist-info/LICENSE.md
arkid_client-0.1.0.dist-info/METADATA
arkid_client-0.1.0.dist-info/WHEEL
arkid_client-0.1.0.dist-info/dependency_links.txt
arkid_client-0.1.0.dist-info/top_level.txt
arkid_client-0.1.0.dist-info/zip-safe
arkid_client-0.1.0.dist-info/RECORD
