Metadata-Version: 2.1
Name: arkid-client
Version: 0.1.0
Summary: ArkID SDk For Python
Home-page: https://github.com/longguikeji/arkid-core
Author: longguikeji
Author-email: rr97390483@dingtalk.com
License: UNKNOWN
Download-URL: https://github.com/longguikeji/arkid-core
Keywords: ArkID SDk Client
Platform: UNKNOWN
Classifier: Development Status :: 5 - Production/Stable
Classifier: Intended Audience :: Developers
Classifier: Topic :: Software Development :: Libraries :: Python Modules
Classifier: Topic :: Internet :: WWW/HTTP
Classifier: License :: OSI Approved :: GNU General Public License (GPL)
Classifier: Operating System :: OS Independent
Classifier: Programming Language :: Python
Classifier: Programming Language :: Python :: 3.6
Requires-Dist: requests (<3.0.0,>=2.9.2)
